README.md
setup.py
cmt/DNN.py
cmt/__init__.py
cmt/config_plots.py
cmt/data_loader.py
cmt/early_stopping.py
cmt/evaluations.py
cmt/gradient.py
cmt/loss_functions.py
cmt/parameters.py
cmt/parse_results.py
cmt/presets.py
cmt/training.py
cmt/training_record_grad.py
pgml_cmt.egg-info/PKG-INFO
pgml_cmt.egg-info/SOURCES.txt
pgml_cmt.egg-info/dependency_links.txt
pgml_cmt.egg-info/not-zip-safe
pgml_cmt.egg-info/top_level.txt