Metadata-Version: 1.0
Name: pgml-cmt
Version: 0.2.1
Summary: Navigating the Generalization Landscape of Neural Networks using Physics: A Case Study in Quantum Mechanics
Home-page: http://shorturl.at/tCZ05
Author: Anonymous Author
Author-email: pgml_cmt@yahoo.com
License: MIT
Platform: UNKNOWN
